mplstyles_seaborn/__init__.py
mplstyles_seaborn/_version.py
mplstyles_seaborn/py.typed
mplstyles_seaborn/styles/seaborn-v0_8-dark-bright-notebook.mplstyle
mplstyles_seaborn/styles/seaborn-v0_8-dark-bright-paper.mplstyle
mplstyles_seaborn/styles/seaborn-v0_8-dark-bright-poster.mplstyle
mplstyles_seaborn/styles/seaborn-v0_8-dark-bright-talk.mplstyle
mplstyles_seaborn/styles/seaborn-v0_8-dark-colorblind-notebook.mplstyle
mplstyles_seaborn/styles/seaborn-v0_8-dark-colorblind-paper.mplstyle
mplstyles_seaborn/styles/seaborn-v0_8-dark-colorblind-poster.mplstyle
mplstyles_seaborn/styles/seaborn-v0_8-dark-colorblind-talk.mplstyle
mplstyles_seaborn/styles/seaborn-v0_8-dark-dark-notebook.mplstyle
mplstyles_seaborn/styles/seaborn-v0_8-dark-dark-paper.mplstyle
mplstyles_seaborn/styles/seaborn-v0_8-dark-dark-poster.mplstyle
mplstyles_seaborn/styles/seaborn-v0_8-dark-dark-talk.mplstyle
mplstyles_seaborn/styles/seaborn-v0_8-dark-deep-notebook.mplstyle
mplstyles_seaborn/styles/seaborn-v0_8-dark-deep-paper.mplstyle
mplstyles_seaborn/styles/seaborn-v0_8-dark-deep-poster.mplstyle
mplstyles_seaborn/styles/seaborn-v0_8-dark-deep-talk.mplstyle
mplstyles_seaborn/styles/seaborn-v0_8-dark-muted-notebook.mplstyle
mplstyles_seaborn/styles/seaborn-v0_8-dark-muted-paper.mplstyle
mplstyles_seaborn/styles/seaborn-v0_8-dark-muted-poster.mplstyle
mplstyles_seaborn/styles/seaborn-v0_8-dark-muted-talk.mplstyle
mplstyles_seaborn/styles/seaborn-v0_8-dark-pastel-notebook.mplstyle
mplstyles_seaborn/styles/seaborn-v0_8-dark-pastel-paper.mplstyle
mplstyles_seaborn/styles/seaborn-v0_8-dark-pastel-poster.mplstyle
mplstyles_seaborn/styles/seaborn-v0_8-dark-pastel-talk.mplstyle
mplstyles_seaborn/styles/seaborn-v0_8-darkgrid-bright-notebook.mplstyle
mplstyles_seaborn/styles/seaborn-v0_8-darkgrid-bright-paper.mplstyle
mplstyles_seaborn/styles/seaborn-v0_8-darkgrid-bright-poster.mplstyle
mplstyles_seaborn/styles/seaborn-v0_8-darkgrid-bright-talk.mplstyle
mplstyles_seaborn-0.2.5.dist-info/licenses/LICENSE
mplstyles_seaborn-0.2.5.dist-info/METADATA
mplstyles_seaborn-0.2.5.dist-info/WHEEL
mplstyles_seaborn-0.2.5.dist-info/top_level.txt
mplstyles_seaborn-0.2.5.dist-info/RECORD
