Metadata-Version: 2.4
Name: mplstyles-seaborn
Version: 0.2.5
Summary: Matplotlib style sheets based on seaborn-v0_8-dark theme with combinable palettes and contexts
Author-email: Masato Onodera <masato.onodera@gmail.com>
License: MIT
Project-URL: Homepage, https://github.com/monodera/mplstyles-seaborn
Project-URL: Repository, https://github.com/monodera/mplstyles-seaborn
Project-URL: Issues, https://github.com/monodera/mplstyles-seaborn/issues
Keywords: matplotlib,seaborn,plotting,visualization,styles
Classifier: Development Status :: 4 - Beta
Classifier: Intended Audience :: Developers
Classifier: Intended Audience :: Science/Research
Classifier: License :: OSI Approved :: MIT License
Classifier: Programming Language :: Python :: 3
Classifier: Programming Language :: Python :: 3.11
Classifier: Programming Language :: Python :: 3.12
Classifier: Topic :: Scientific/Engineering :: Visualization
Classifier: Typing :: Typed
Requires-Python: >=3.11
License-File: LICENSE
Requires-Dist: matplotlib>=3.8
Provides-Extra: dev
Requires-Dist: seaborn>=0.11; extra == "dev"
Provides-Extra: test
Requires-Dist: pytest>=7.0; extra == "test"
Requires-Dist: pytest-cov>=4.0; extra == "test"
Dynamic: license-file
